tinymce_filebrowser/__init__.py
tinymce_filebrowser/admin.py
tinymce_filebrowser/apps.py
tinymce_filebrowser/forms.py
tinymce_filebrowser/models.py
tinymce_filebrowser/tests.py
tinymce_filebrowser/urls.py
tinymce_filebrowser/views.py
tinymce_filebrowser/migrations/0001_initial.py
tinymce_filebrowser/migrations/__init__.py
tinymce_filebrowser_django-1.0.3.dist-info/LICENSE
tinymce_filebrowser_django-1.0.3.dist-info/METADATA
tinymce_filebrowser_django-1.0.3.dist-info/WHEEL
tinymce_filebrowser_django-1.0.3.dist-info/top_level.txt
tinymce_filebrowser_django-1.0.3.dist-info/RECORD
